LICENSE.txt
MANIFEST.in
README.md
README.rst
readme.md
setup.cfg
setup.py
django_pubtools.egg-info/PKG-INFO
django_pubtools.egg-info/SOURCES.txt
django_pubtools.egg-info/dependency_links.txt
django_pubtools.egg-info/not-zip-safe
django_pubtools.egg-info/requires.txt
django_pubtools.egg-info/top_level.txt
pubtools/__init__.py
pubtools/_version.py
pubtools/admin.py
pubtools/models.py
tests/__init__.py
tests/admin.py
tests/models.py
tests/test_settings.py
tests/tests.py
tests/urls.py
tests/views.py