Metadata-Version: 1.1
Name: django-pubtools
Version: 2.0.4
Summary: A set of reusable base classes and helpers for django
Home-page: https://github.com/gregplaysguitar/django-pubtools
Author: Greg Brown
Author-email: greg@gregbrown.co.nz
License: UNKNOWN
Keywords: django,publishing
Platform: any
Classifier: Development Status :: 5 - Production/Stable
Classifier: Environment :: Web Environment
Classifier: Intended Audience :: Developers
Classifier: Operating System :: OS Independent
Classifier: Programming Language :: Python
Classifier: Topic :: Internet :: WWW/HTTP :: Dynamic Content
Classifier: Framework :: Django
